ultraflow-0.2.0.dist-info/METADATA
ultraflow-0.2.0.dist-info/WHEEL
ultraflow-0.2.0.dist-info/entry_points.txt
ultraflow/__init__.py
ultraflow/cli/__init__.py
ultraflow/cli/main.py
ultraflow/core/__init__.py
ultraflow/core/example.prompty
ultraflow/core/flow.py
ultraflow/core/start_flow.py
ultraflow/core/utils.py
ultraflow-0.2.0.dist-info/RECORD
