Metadata-Version: 2.1
Name: UltraFlow
Version: 0.2.0
Summary: A comprehensive toolkit for streamlined development, testing, and deployment of prompt.
Author-Email: Henry He <henryhyn@163.com>
License: MIT
Project-URL: Repository, https://github.com/enthusa/UltraFlow
Requires-Python: !=3.13.*,>=3.9.2
Requires-Dist: marshmallow==3.23.3
Requires-Dist: promptflow==1.16.2
Requires-Dist: json-repair==0.44.1
